LICENSE
README.md
setup.cfg
setup.py
vocabtrimmer/__init__.py
vocabtrimmer/base_trimmer.py
vocabtrimmer/util.py
vocabtrimmer/vocab_miner.py
vocabtrimmer.egg-info/PKG-INFO
vocabtrimmer.egg-info/SOURCES.txt
vocabtrimmer.egg-info/dependency_links.txt
vocabtrimmer.egg-info/entry_points.txt
vocabtrimmer.egg-info/requires.txt
vocabtrimmer.egg-info/top_level.txt
vocabtrimmer/cl/__init__.py
vocabtrimmer/cl/trimming.py