Metadata-Version: 2.1
Name: vocabtrimmer
Version: 0.0.2
Summary: Trimming vocabulary of pre-trained multilingual language models to language localization.
Home-page: https://github.com/asahi417/lm-vocab-trmmer
Author: Asahi Ushio
Author-email: asahi1992ushio@gmail.com
License: MIT License
Download-URL: https://github.com/asahi417/lm-vocab-trmmer/archive/v0.0.2.tar.gz
Keywords: language model,t5,gpt3,bertnlp,multilingual,efficient-model
Platform: UNKNOWN
Classifier: Development Status :: 4 - Beta
Classifier: Intended Audience :: Developers
Classifier: Intended Audience :: Science/Research
Classifier: Topic :: Scientific/Engineering
Classifier: License :: OSI Approved :: MIT License
Classifier: Programming Language :: Python :: 3
Requires-Python: >=3.6
License-File: LICENSE
